desafio_processamento_de_imagem/__init__.py
desafio_processamento_de_imagem/module1_name/__init__.py
desafio_processamento_de_imagem/module1_name/file1_name.py
desafio_processamento_de_imagem/module1_name/file2_name.py
desafio_processamento_de_imagem/module2_name/__init__.py
desafio_processamento_de_imagem/module2_name/file1_name.py
desafio_processamento_de_imagem/module2_name/file2_name.py
desafio_processamento_de_imagem-0.0.1.dist-info/METADATA
desafio_processamento_de_imagem-0.0.1.dist-info/WHEEL
desafio_processamento_de_imagem-0.0.1.dist-info/top_level.txt
desafio_processamento_de_imagem-0.0.1.dist-info/RECORD
