Metadata-Version: 2.1
Name: desafio-processamento-de-imagem
Version: 0.0.1
Summary: My short description
Home-page: https://github.com/MichelleMapelli/repositorio-dio
Author: Michelle Trigueiro
Author-email: mi.mapelli@gmail.com
License: UNKNOWN
Platform: UNKNOWN
Requires-Python: >=3.8
